aaai-0.1.2.dist-info/METADATA
aaai-0.1.2.dist-info/WHEEL
aaai/__init__.py
aaai-0.1.2.dist-info/RECORD
